.coveragerc
.gitignore
AUTHORS.rst
CHANGELOG.rst
LICENSE.txt
README.rst
requirements.txt
setup.cfg
setup.py
docs/Makefile
docs/authors.rst
docs/changelog.rst
docs/conf.py
docs/index.rst
docs/license.rst
docs/_static/.gitignore
src/named_redirect/__init__.py
src/named_redirect/skeleton.py
src/named_redirect.egg-info/PKG-INFO
src/named_redirect.egg-info/SOURCES.txt
src/named_redirect.egg-info/dependency_links.txt
src/named_redirect.egg-info/entry_points.txt
src/named_redirect.egg-info/not-zip-safe
src/named_redirect.egg-info/top_level.txt
tests/conftest.py
tests/test_skeleton.py