Metadata-Version: 1.1
Name: named-redirect
Version: 0.5.2
Summary: DNS jail for IIAB/bind9 if there is no internet
Home-page: http://...
Author: Anish Mangal
Author-email: anishmg@umich.edu
License: gpl3
Platform: any
Classifier: Development Status :: 4 - Beta
Classifier: Programming Language :: Python
